overcast_parser/__init__.py
overcast_parser/overcast_parser.py
overcast_parser/utils.py
overcast_parser/itunes_podcast_rss/__init__.py
overcast_parser/itunes_podcast_rss/extract.py
overcast_parser-0.1.0.dist-info/LICENSE.txt
overcast_parser-0.1.0.dist-info/METADATA
overcast_parser-0.1.0.dist-info/WHEEL
overcast_parser-0.1.0.dist-info/top_level.txt
overcast_parser-0.1.0.dist-info/RECORD
