Metadata-Version: 2.1
Name: overcast_parser
Version: 0.1.0
Summary: Overcast podcast link parser especially for pythonista.
Home-page: https://github.com/hbmartin/overcast_parser
Author: Harold Martin
Author-email: harold.martin@gmail.com
License: MIT
Project-URL: Bug Reports, https://github.com/hbmartin/overcast_parser/issues
Keywords: podcast,parser,rss,feed,pythonista,overcast,shortcuts,ios
Classifier: Development Status :: 4 - Beta
Classifier: Intended Audience :: Developers
Classifier: Operating System :: iOS
Classifier: Topic :: Software Development :: Libraries :: Python Modules
Classifier: Topic :: Text Processing :: Markup :: XML
Classifier: License :: OSI Approved :: MIT License
Classifier: Programming Language :: Python :: 3
Classifier: Programming Language :: Python :: 3.10
Classifier: Programming Language :: Python :: 3.11
Classifier: Programming Language :: Python :: 3.12
Classifier: Typing :: Typed
License-File: LICENSE.txt
Requires-Dist: podcastparser
Requires-Dist: requests
Provides-Extra: dev
Requires-Dist: black ; extra == 'dev'
Requires-Dist: pythonista-stubs ; extra == 'dev'
Provides-Extra: lint
Requires-Dist: ruff ; extra == 'lint'
Requires-Dist: pyroma ; extra == 'lint'
Requires-Dist: pytype ; extra == 'lint'
Requires-Dist: types-python-dateutil ; extra == 'lint'
Requires-Dist: types-requests ; extra == 'lint'
